CLICopti/CLICopti.py
CLICopti/CellBase.py
CLICopti/CellParams.py
CLICopti/Constants.py
CLICopti/RFStructure.py
CLICopti/TD_12GHz_v1.dat
CLICopti/TD_12GHz_v2.dat
CLICopti/TD_30GHz.dat
CLICopti/_CLICopti.cpython-312-x86_64-linux-gnu.so
CLICopti/__init__.py
tests/test_cellLibrary.py
tests/test_structureLibrary.py
tests/testutils.py
clicopti-2.2.1.dist-info/METADATA
clicopti-2.2.1.dist-info/WHEEL
clicopti-2.2.1.dist-info/top_level.txt
clicopti-2.2.1.dist-info/RECORD
clicopti-2.2.1.dist-info/licenses/LICENSE
