Metadata-Version: 2.4
Name: CLICopti
Version: 2.2.1
Author: Daniel Schulte, Alexej Grudiev, Andrea Latina, Jim Ögren
Author-email: Kyrre Sjobak <k.n.sjobak@fys.uio.no>
License-Expression: LGPL-3.0-or-later
Requires-Python: >=3
License-File: LICENSE
Requires-Dist: numpy
Dynamic: license-file
